qm40_dataset_for_ml/Lmod_run.py
qm40_dataset_for_ml/QM40data_search.py
qm40_dataset_for_ml/__init__.py
qm40_dataset_for_ml/gaussian_info_extractor.py
qm40_dataset_for_ml/utils.py
QM40_dataset_for_ML-0.0.1.dist-info/LICENSE
QM40_dataset_for_ML-0.0.1.dist-info/METADATA
QM40_dataset_for_ML-0.0.1.dist-info/WHEEL
QM40_dataset_for_ML-0.0.1.dist-info/entry_points.txt
QM40_dataset_for_ML-0.0.1.dist-info/top_level.txt
QM40_dataset_for_ML-0.0.1.dist-info/RECORD
